etpay_sdk
