Metadata-Version: 2.1
Name: etpay-sdk
Version: 1.0.1
Summary: Etpay SDK for Python
Home-page: UNKNOWN
License: BSD
Platform: UNKNOWN
